pyaidoop/__init__.py
pyaidoop/aruco/__init__.py
pyaidoop/aruco/aruco_advanced_pose.py
pyaidoop/aruco/aruco_detect.py
pyaidoop/calibration/__init__.py
pyaidoop/calibration/calibcamera.py
pyaidoop/calibration/calibcamera_aruco.py
pyaidoop/calibration/calibhandeye_auto_move.py
pyaidoop/calibration/calibhandeye_handeye.py
pyaidoop/camera/__init__.py
pyaidoop/camera/camera_dev_abc.py
pyaidoop/camera/camera_dev_azure_kinnect.py
pyaidoop/camera/camera_dev_opencv.py
pyaidoop/camera/camera_dev_realsense.py
pyaidoop/camera/camera_videocapture.py
pyaidoop/etc/__init__.py
pyaidoop/etc/hm_util.py
pyaidoop/log/__init__.py
pyaidoop/log/custom_timed_rotating_handler.py
pyaidoop/log/logger.py
pyaidoop/robot/__init__.py
pyaidoop/robot/robot_arm.py
pyaidoop/robot/robot_arm_dev.py
pyaidoop/robot/robot_dev_indydcp.py
pyaidoop_light-0.1.0.dist-info/LICENSE
pyaidoop_light-0.1.0.dist-info/METADATA
pyaidoop_light-0.1.0.dist-info/WHEEL
pyaidoop_light-0.1.0.dist-info/top_level.txt
pyaidoop_light-0.1.0.dist-info/RECORD
